drim2p/__about__.py
drim2p/__init__.py
drim2p/cli_utils.py
drim2p/logs.py
drim2p/models.py
drim2p/py.typed
drim2p/convert/__init__.py
drim2p/convert/raw.py
drim2p/deltaf/__init__.py
drim2p/deltaf/errors.py
drim2p/draw/__init__.py
drim2p/draw/roi.py
drim2p/extract/__init__.py
drim2p/extract/signal.py
drim2p/io/__init__.py
drim2p/io/errors.py
drim2p/io/raw.py
drim2p/motion/__init__.py
drim2p/motion/correct.py
drim2p-1.0.1.dist-info/METADATA
drim2p-1.0.1.dist-info/WHEEL
drim2p-1.0.1.dist-info/entry_points.txt
drim2p-1.0.1.dist-info/licenses/LICENSE
drim2p-1.0.1.dist-info/RECORD
